{
  "id": "dbe2c2ee-74d7-4287-8e57-a9896a3d09fd",
  "title": "Article: FINAL DEBUG TEST",
  "content_type": "article",
  "content_format": "markdown",
  "status": "draft",
  "workflow_id": "a8a01c1e-1933-4939-a6d2-f00f17f0c86e",
  "client_profile": "siebert",
  "target_audience": "",
  "topic": "",
  "tags": [],
  "metrics": {
    "word_count": 0,
    "character_count": 0,
    "reading_time_minutes": 0.0,
    "readability_score": null,
    "sentiment_score": null
  },
  "metadata": {
    "workflow_type": "enhanced_article",
    "generation_params": {
      "topic": "FINAL DEBUG TEST",
      "content_type": "article",
      "content_format": "markdown",
      "generation_mode": "standard",
      "target_word_count": 300,
      "max_word_count": null,
      "min_word_count": null,
      "include_sources": true,
      "include_statistics": true,
      "include_examples": true,
      "tone": "professional",
      "style": "informative",
      "target_audience": "general",
      "language": "en",
      "seo_keywords": [],
      "custom_instructions": "",
      "metadata": {}
    },
    "workflow_summary": {
      "topic": "FINAL DEBUG TEST",
      "client": "siebert",
      "target_audience": "general",
      "word_count": 181,
      "research_depth": "basic",
      "includes_data": true,
      "includes_trends": false
    },
    "dynamic_workflow": true
  },
  "created_at": "2025-07-27T09:05:50.184588",
  "updated_at": "2025-07-27T09:05:50.184589",
  "published_at": null,
  "version": 1
}